{
  "variant": {
    "label": "RelWithDebInfo",
    "keywordSettings": {
      "buildType": "reldeb"
    },
    "description": "Perform optimizations AND include debugging information"
  },
  "activeEnvironments": [],
  "codeModel": {
    "configurations": [
      {
        "name": "RelWithDebInfo",
        "projects": [
          {
            "buildDirectory": "/home/kevinah95/Documents/SO-Pr2-Synchronization/build",
            "name": "SO-Pr2-Synchronization",
            "sourceDirectory": "/home/kevinah95/Documents/SO-Pr2-Synchronization",
            "targets": [
              {
                "buildDirectory": "/home/kevinah95/Documents/SO-Pr2-Synchronization/build",
                "fileGroups": [
                  {
                    "isGenerated": true,
                    "sources": [
                      "build/CMakeFiles/NightlyBuild",
                      "build/CMakeFiles/NightlyBuild.rule"
                    ]
                  }
                ],
                "fullName": "NightlyBuild",
                "name": "NightlyBuild",
                "sourceDirectory": "/home/kevinah95/Documents/SO-Pr2-Synchronization",
                "type": "UTILITY"
              },
              {
                "buildDirectory": "/home/kevinah95/Documents/SO-Pr2-Synchronization/build",
                "fileGroups": [
                  {
                    "isGenerated": true,
                    "sources": [
                      "build/CMakeFiles/NightlyStart",
                      "build/CMakeFiles/NightlyStart.rule"
                    ]
                  }
                ],
                "fullName": "NightlyStart",
                "name": "NightlyStart",
                "sourceDirectory": "/home/kevinah95/Documents/SO-Pr2-Synchronization",
                "type": "UTILITY"
              },
              {
                "buildDirectory": "/home/kevinah95/Documents/SO-Pr2-Synchronization/build",
                "fileGroups": [
                  {
                    "isGenerated": true,
                    "sources": [
                      "build/CMakeFiles/NightlyMemoryCheck",
                      "build/CMakeFiles/NightlyMemoryCheck.rule"
                    ]
                  }
                ],
                "fullName": "NightlyMemoryCheck",
                "name": "NightlyMemoryCheck",
                "sourceDirectory": "/home/kevinah95/Documents/SO-Pr2-Synchronization",
                "type": "UTILITY"
              },
              {
                "buildDirectory": "/home/kevinah95/Documents/SO-Pr2-Synchronization/build",
                "fileGroups": [
                  {
                    "isGenerated": true,
                    "sources": [
                      "build/CMakeFiles/NightlyMemCheck",
                      "build/CMakeFiles/NightlyMemCheck.rule"
                    ]
                  }
                ],
                "fullName": "NightlyMemCheck",
                "name": "NightlyMemCheck",
                "sourceDirectory": "/home/kevinah95/Documents/SO-Pr2-Synchronization",
                "type": "UTILITY"
              },
              {
                "buildDirectory": "/home/kevinah95/Documents/SO-Pr2-Synchronization/build",
                "fileGroups": [
                  {
                    "isGenerated": true,
                    "sources": [
                      "build/CMakeFiles/ExperimentalUpdate",
                      "build/CMakeFiles/ExperimentalUpdate.rule"
                    ]
                  }
                ],
                "fullName": "ExperimentalUpdate",
                "name": "ExperimentalUpdate",
                "sourceDirectory": "/home/kevinah95/Documents/SO-Pr2-Synchronization",
                "type": "UTILITY"
              },
              {
                "buildDirectory": "/home/kevinah95/Documents/SO-Pr2-Synchronization/build",
                "fileGroups": [
                  {
                    "isGenerated": true,
                    "sources": [
                      "build/CMakeFiles/ExperimentalConfigure",
                      "build/CMakeFiles/ExperimentalConfigure.rule"
                    ]
                  }
                ],
                "fullName": "ExperimentalConfigure",
                "name": "ExperimentalConfigure",
                "sourceDirectory": "/home/kevinah95/Documents/SO-Pr2-Synchronization",
                "type": "UTILITY"
              },
              {
                "buildDirectory": "/home/kevinah95/Documents/SO-Pr2-Synchronization/build",
                "fileGroups": [
                  {
                    "isGenerated": true,
                    "sources": [
                      "build/CMakeFiles/ExperimentalCoverage",
                      "build/CMakeFiles/ExperimentalCoverage.rule"
                    ]
                  }
                ],
                "fullName": "ExperimentalCoverage",
                "name": "ExperimentalCoverage",
                "sourceDirectory": "/home/kevinah95/Documents/SO-Pr2-Synchronization",
                "type": "UTILITY"
              },
              {
                "buildDirectory": "/home/kevinah95/Documents/SO-Pr2-Synchronization/build",
                "fileGroups": [
                  {
                    "isGenerated": true,
                    "sources": [
                      "build/CMakeFiles/ExperimentalBuild",
                      "build/CMakeFiles/ExperimentalBuild.rule"
                    ]
                  }
                ],
                "fullName": "ExperimentalBuild",
                "name": "ExperimentalBuild",
                "sourceDirectory": "/home/kevinah95/Documents/SO-Pr2-Synchronization",
                "type": "UTILITY"
              },
              {
                "buildDirectory": "/home/kevinah95/Documents/SO-Pr2-Synchronization/build",
                "fileGroups": [
                  {
                    "isGenerated": true,
                    "sources": [
                      "build/CMakeFiles/NightlyConfigure",
                      "build/CMakeFiles/NightlyConfigure.rule"
                    ]
                  }
                ],
                "fullName": "NightlyConfigure",
                "name": "NightlyConfigure",
                "sourceDirectory": "/home/kevinah95/Documents/SO-Pr2-Synchronization",
                "type": "UTILITY"
              },
              {
                "buildDirectory": "/home/kevinah95/Documents/SO-Pr2-Synchronization/build",
                "fileGroups": [
                  {
                    "isGenerated": true,
                    "sources": [
                      "build/CMakeFiles/ExperimentalStart",
                      "build/CMakeFiles/ExperimentalStart.rule"
                    ]
                  }
                ],
                "fullName": "ExperimentalStart",
                "name": "ExperimentalStart",
                "sourceDirectory": "/home/kevinah95/Documents/SO-Pr2-Synchronization",
                "type": "UTILITY"
              },
              {
                "buildDirectory": "/home/kevinah95/Documents/SO-Pr2-Synchronization/build",
                "fileGroups": [
                  {
                    "isGenerated": true,
                    "sources": [
                      "build/CMakeFiles/ContinuousConfigure",
                      "build/CMakeFiles/ContinuousConfigure.rule"
                    ]
                  }
                ],
                "fullName": "ContinuousConfigure",
                "name": "ContinuousConfigure",
                "sourceDirectory": "/home/kevinah95/Documents/SO-Pr2-Synchronization",
                "type": "UTILITY"
              },
              {
                "buildDirectory": "/home/kevinah95/Documents/SO-Pr2-Synchronization/build",
                "fileGroups": [
                  {
                    "isGenerated": true,
                    "sources": [
                      "build/CMakeFiles/NightlyCoverage",
                      "build/CMakeFiles/NightlyCoverage.rule"
                    ]
                  }
                ],
                "fullName": "NightlyCoverage",
                "name": "NightlyCoverage",
                "sourceDirectory": "/home/kevinah95/Documents/SO-Pr2-Synchronization",
                "type": "UTILITY"
              },
              {
                "buildDirectory": "/home/kevinah95/Documents/SO-Pr2-Synchronization/build",
                "fileGroups": [
                  {
                    "isGenerated": true,
                    "sources": [
                      "build/CMakeFiles/ExperimentalTest",
                      "build/CMakeFiles/ExperimentalTest.rule"
                    ]
                  }
                ],
                "fullName": "ExperimentalTest",
                "name": "ExperimentalTest",
                "sourceDirectory": "/home/kevinah95/Documents/SO-Pr2-Synchronization",
                "type": "UTILITY"
              },
              {
                "artifacts": [
                  "/home/kevinah95/Documents/SO-Pr2-Synchronization/build/Producer"
                ],
                "buildDirectory": "/home/kevinah95/Documents/SO-Pr2-Synchronization/build",
                "fileGroups": [
                  {
                    "compileFlags": "-O2 -g -DNDEBUG   -pthread",
                    "includePath": [
                      {
                        "path": "/home/kevinah95/Documents/SO-Pr2-Synchronization/lib"
                      },
                      {
                        "path": "/home/kevinah95/Documents/SO-Pr2-Synchronization/include"
                      }
                    ],
                    "isGenerated": false,
                    "language": "C",
                    "sources": [
                      "producer.c"
                    ]
                  }
                ],
                "fullName": "Producer",
                "linkFlags": "-rdynamic",
                "linkLanguageFlags": "-O2 -g -DNDEBUG",
                "linkLibraries": "lib/liblib.a include/libinclude.a -pthread",
                "linkerLanguage": "C",
                "name": "Producer",
                "sourceDirectory": "/home/kevinah95/Documents/SO-Pr2-Synchronization",
                "type": "EXECUTABLE"
              },
              {
                "buildDirectory": "/home/kevinah95/Documents/SO-Pr2-Synchronization/build",
                "fileGroups": [
                  {
                    "isGenerated": true,
                    "sources": [
                      "build/CMakeFiles/ExperimentalMemCheck",
                      "build/CMakeFiles/ExperimentalMemCheck.rule"
                    ]
                  }
                ],
                "fullName": "ExperimentalMemCheck",
                "name": "ExperimentalMemCheck",
                "sourceDirectory": "/home/kevinah95/Documents/SO-Pr2-Synchronization",
                "type": "UTILITY"
              },
              {
                "buildDirectory": "/home/kevinah95/Documents/SO-Pr2-Synchronization/build",
                "fileGroups": [
                  {
                    "isGenerated": true,
                    "sources": [
                      "build/CMakeFiles/Experimental",
                      "build/CMakeFiles/Experimental.rule"
                    ]
                  }
                ],
                "fullName": "Experimental",
                "name": "Experimental",
                "sourceDirectory": "/home/kevinah95/Documents/SO-Pr2-Synchronization",
                "type": "UTILITY"
              },
              {
                "buildDirectory": "/home/kevinah95/Documents/SO-Pr2-Synchronization/build",
                "fileGroups": [
                  {
                    "isGenerated": true,
                    "sources": [
                      "build/CMakeFiles/NightlySubmit",
                      "build/CMakeFiles/NightlySubmit.rule"
                    ]
                  }
                ],
                "fullName": "NightlySubmit",
                "name": "NightlySubmit",
                "sourceDirectory": "/home/kevinah95/Documents/SO-Pr2-Synchronization",
                "type": "UTILITY"
              },
              {
                "buildDirectory": "/home/kevinah95/Documents/SO-Pr2-Synchronization/build",
                "fileGroups": [
                  {
                    "isGenerated": true,
                    "sources": [
                      "build/CMakeFiles/ExperimentalSubmit",
                      "build/CMakeFiles/ExperimentalSubmit.rule"
                    ]
                  }
                ],
                "fullName": "ExperimentalSubmit",
                "name": "ExperimentalSubmit",
                "sourceDirectory": "/home/kevinah95/Documents/SO-Pr2-Synchronization",
                "type": "UTILITY"
              },
              {
                "artifacts": [
                  "/home/kevinah95/Documents/SO-Pr2-Synchronization/build/Initializer"
                ],
                "buildDirectory": "/home/kevinah95/Documents/SO-Pr2-Synchronization/build",
                "fileGroups": [
                  {
                    "compileFlags": "-O2 -g -DNDEBUG   -pthread",
                    "includePath": [
                      {
                        "path": "/home/kevinah95/Documents/SO-Pr2-Synchronization/lib"
                      },
                      {
                        "path": "/home/kevinah95/Documents/SO-Pr2-Synchronization/include"
                      }
                    ],
                    "isGenerated": false,
                    "language": "C",
                    "sources": [
                      "initializer.c"
                    ]
                  }
                ],
                "fullName": "Initializer",
                "linkFlags": "-rdynamic",
                "linkLanguageFlags": "-O2 -g -DNDEBUG",
                "linkLibraries": "lib/liblib.a include/libinclude.a -pthread",
                "linkerLanguage": "C",
                "name": "Initializer",
                "sourceDirectory": "/home/kevinah95/Documents/SO-Pr2-Synchronization",
                "type": "EXECUTABLE"
              },
              {
                "buildDirectory": "/home/kevinah95/Documents/SO-Pr2-Synchronization/build",
                "fileGroups": [
                  {
                    "isGenerated": true,
                    "sources": [
                      "build/CMakeFiles/ContinuousStart",
                      "build/CMakeFiles/ContinuousStart.rule"
                    ]
                  }
                ],
                "fullName": "ContinuousStart",
                "name": "ContinuousStart",
                "sourceDirectory": "/home/kevinah95/Documents/SO-Pr2-Synchronization",
                "type": "UTILITY"
              },
              {
                "buildDirectory": "/home/kevinah95/Documents/SO-Pr2-Synchronization/build",
                "fileGroups": [
                  {
                    "isGenerated": true,
                    "sources": [
                      "build/CMakeFiles/ContinuousUpdate",
                      "build/CMakeFiles/ContinuousUpdate.rule"
                    ]
                  }
                ],
                "fullName": "ContinuousUpdate",
                "name": "ContinuousUpdate",
                "sourceDirectory": "/home/kevinah95/Documents/SO-Pr2-Synchronization",
                "type": "UTILITY"
              },
              {
                "buildDirectory": "/home/kevinah95/Documents/SO-Pr2-Synchronization/build",
                "fileGroups": [
                  {
                    "isGenerated": true,
                    "sources": [
                      "build/CMakeFiles/NightlyTest",
                      "build/CMakeFiles/NightlyTest.rule"
                    ]
                  }
                ],
                "fullName": "NightlyTest",
                "name": "NightlyTest",
                "sourceDirectory": "/home/kevinah95/Documents/SO-Pr2-Synchronization",
                "type": "UTILITY"
              },
              {
                "artifacts": [
                  "/home/kevinah95/Documents/SO-Pr2-Synchronization/build/Spy"
                ],
                "buildDirectory": "/home/kevinah95/Documents/SO-Pr2-Synchronization/build",
                "fileGroups": [
                  {
                    "compileFlags": "-O2 -g -DNDEBUG   -pthread",
                    "includePath": [
                      {
                        "path": "/home/kevinah95/Documents/SO-Pr2-Synchronization/lib"
                      },
                      {
                        "path": "/home/kevinah95/Documents/SO-Pr2-Synchronization/include"
                      }
                    ],
                    "isGenerated": false,
                    "language": "C",
                    "sources": [
                      "spy.c"
                    ]
                  }
                ],
                "fullName": "Spy",
                "linkFlags": "-rdynamic",
                "linkLanguageFlags": "-O2 -g -DNDEBUG",
                "linkLibraries": "lib/liblib.a include/libinclude.a -pthread",
                "linkerLanguage": "C",
                "name": "Spy",
                "sourceDirectory": "/home/kevinah95/Documents/SO-Pr2-Synchronization",
                "type": "EXECUTABLE"
              },
              {
                "buildDirectory": "/home/kevinah95/Documents/SO-Pr2-Synchronization/build",
                "fileGroups": [
                  {
                    "isGenerated": true,
                    "sources": [
                      "build/CMakeFiles/NightlyUpdate",
                      "build/CMakeFiles/NightlyUpdate.rule"
                    ]
                  }
                ],
                "fullName": "NightlyUpdate",
                "name": "NightlyUpdate",
                "sourceDirectory": "/home/kevinah95/Documents/SO-Pr2-Synchronization",
                "type": "UTILITY"
              },
              {
                "buildDirectory": "/home/kevinah95/Documents/SO-Pr2-Synchronization/build",
                "fileGroups": [
                  {
                    "isGenerated": true,
                    "sources": [
                      "build/CMakeFiles/Continuous",
                      "build/CMakeFiles/Continuous.rule"
                    ]
                  }
                ],
                "fullName": "Continuous",
                "name": "Continuous",
                "sourceDirectory": "/home/kevinah95/Documents/SO-Pr2-Synchronization",
                "type": "UTILITY"
              },
              {
                "buildDirectory": "/home/kevinah95/Documents/SO-Pr2-Synchronization/build",
                "fileGroups": [
                  {
                    "isGenerated": true,
                    "sources": [
                      "build/CMakeFiles/ContinuousBuild",
                      "build/CMakeFiles/ContinuousBuild.rule"
                    ]
                  }
                ],
                "fullName": "ContinuousBuild",
                "name": "ContinuousBuild",
                "sourceDirectory": "/home/kevinah95/Documents/SO-Pr2-Synchronization",
                "type": "UTILITY"
              },
              {
                "buildDirectory": "/home/kevinah95/Documents/SO-Pr2-Synchronization/build",
                "fileGroups": [
                  {
                    "isGenerated": true,
                    "sources": [
                      "build/CMakeFiles/ContinuousMemCheck",
                      "build/CMakeFiles/ContinuousMemCheck.rule"
                    ]
                  }
                ],
                "fullName": "ContinuousMemCheck",
                "name": "ContinuousMemCheck",
                "sourceDirectory": "/home/kevinah95/Documents/SO-Pr2-Synchronization",
                "type": "UTILITY"
              },
              {
                "buildDirectory": "/home/kevinah95/Documents/SO-Pr2-Synchronization/build",
                "fileGroups": [
                  {
                    "isGenerated": true,
                    "sources": [
                      "build/CMakeFiles/Nightly",
                      "build/CMakeFiles/Nightly.rule"
                    ]
                  }
                ],
                "fullName": "Nightly",
                "name": "Nightly",
                "sourceDirectory": "/home/kevinah95/Documents/SO-Pr2-Synchronization",
                "type": "UTILITY"
              },
              {
                "artifacts": [
                  "/home/kevinah95/Documents/SO-Pr2-Synchronization/build/Binnacle"
                ],
                "buildDirectory": "/home/kevinah95/Documents/SO-Pr2-Synchronization/build",
                "fileGroups": [
                  {
                    "compileFlags": "-O2 -g -DNDEBUG  ",
                    "includePath": [
                      {
                        "path": "/home/kevinah95/Documents/SO-Pr2-Synchronization/lib"
                      },
                      {
                        "path": "/home/kevinah95/Documents/SO-Pr2-Synchronization/include"
                      }
                    ],
                    "isGenerated": false,
                    "language": "C",
                    "sources": [
                      "binnacle.c"
                    ]
                  }
                ],
                "fullName": "Binnacle",
                "linkFlags": "-rdynamic",
                "linkLanguageFlags": "-O2 -g -DNDEBUG",
                "linkerLanguage": "C",
                "name": "Binnacle",
                "sourceDirectory": "/home/kevinah95/Documents/SO-Pr2-Synchronization",
                "type": "EXECUTABLE"
              },
              {
                "artifacts": [
                  "/home/kevinah95/Documents/SO-Pr2-Synchronization/build/Killer"
                ],
                "buildDirectory": "/home/kevinah95/Documents/SO-Pr2-Synchronization/build",
                "fileGroups": [
                  {
                    "compileFlags": "-O2 -g -DNDEBUG   -pthread",
                    "includePath": [
                      {
                        "path": "/home/kevinah95/Documents/SO-Pr2-Synchronization/lib"
                      },
                      {
                        "path": "/home/kevinah95/Documents/SO-Pr2-Synchronization/include"
                      }
                    ],
                    "isGenerated": false,
                    "language": "C",
                    "sources": [
                      "killer.c"
                    ]
                  }
                ],
                "fullName": "Killer",
                "linkFlags": "-rdynamic",
                "linkLanguageFlags": "-O2 -g -DNDEBUG",
                "linkLibraries": "-pthread",
                "linkerLanguage": "C",
                "name": "Killer",
                "sourceDirectory": "/home/kevinah95/Documents/SO-Pr2-Synchronization",
                "type": "EXECUTABLE"
              },
              {
                "buildDirectory": "/home/kevinah95/Documents/SO-Pr2-Synchronization/build",
                "fileGroups": [
                  {
                    "isGenerated": true,
                    "sources": [
                      "build/CMakeFiles/ContinuousSubmit",
                      "build/CMakeFiles/ContinuousSubmit.rule"
                    ]
                  }
                ],
                "fullName": "ContinuousSubmit",
                "name": "ContinuousSubmit",
                "sourceDirectory": "/home/kevinah95/Documents/SO-Pr2-Synchronization",
                "type": "UTILITY"
              },
              {
                "buildDirectory": "/home/kevinah95/Documents/SO-Pr2-Synchronization/build",
                "fileGroups": [
                  {
                    "isGenerated": true,
                    "sources": [
                      "build/CMakeFiles/ContinuousCoverage",
                      "build/CMakeFiles/ContinuousCoverage.rule"
                    ]
                  }
                ],
                "fullName": "ContinuousCoverage",
                "name": "ContinuousCoverage",
                "sourceDirectory": "/home/kevinah95/Documents/SO-Pr2-Synchronization",
                "type": "UTILITY"
              },
              {
                "buildDirectory": "/home/kevinah95/Documents/SO-Pr2-Synchronization/build",
                "fileGroups": [
                  {
                    "isGenerated": true,
                    "sources": [
                      "build/CMakeFiles/ContinuousTest",
                      "build/CMakeFiles/ContinuousTest.rule"
                    ]
                  }
                ],
                "fullName": "ContinuousTest",
                "name": "ContinuousTest",
                "sourceDirectory": "/home/kevinah95/Documents/SO-Pr2-Synchronization",
                "type": "UTILITY"
              },
              {
                "artifacts": [
                  "/home/kevinah95/Documents/SO-Pr2-Synchronization/build/lib/liblib.a"
                ],
                "buildDirectory": "/home/kevinah95/Documents/SO-Pr2-Synchronization/build/lib",
                "fileGroups": [
                  {
                    "compileFlags": "-O2 -g -DNDEBUG  ",
                    "includePath": [
                      {
                        "path": "/home/kevinah95/Documents/SO-Pr2-Synchronization/lib"
                      }
                    ],
                    "isGenerated": false,
                    "language": "C",
                    "sources": [
                      "parson.c",
                      "slog.c"
                    ]
                  }
                ],
                "fullName": "liblib.a",
                "linkerLanguage": "C",
                "name": "lib",
                "sourceDirectory": "/home/kevinah95/Documents/SO-Pr2-Synchronization/lib",
                "type": "STATIC_LIBRARY"
              },
              {
                "artifacts": [
                  "/home/kevinah95/Documents/SO-Pr2-Synchronization/build/include/libinclude.a"
                ],
                "buildDirectory": "/home/kevinah95/Documents/SO-Pr2-Synchronization/build/include",
                "fileGroups": [
                  {
                    "compileFlags": "-O2 -g -DNDEBUG  ",
                    "includePath": [
                      {
                        "path": "/home/kevinah95/Documents/SO-Pr2-Synchronization/lib"
                      },
                      {
                        "path": "/home/kevinah95/Documents/SO-Pr2-Synchronization/include"
                      }
                    ],
                    "isGenerated": false,
                    "language": "C",
                    "sources": [
                      "random.c",
                      "algorithms.c"
                    ]
                  }
                ],
                "fullName": "libinclude.a",
                "linkerLanguage": "C",
                "name": "include",
                "sourceDirectory": "/home/kevinah95/Documents/SO-Pr2-Synchronization/include",
                "type": "STATIC_LIBRARY"
              }
            ]
          }
        ]
      }
    ],
    "cookie": "0.10764390421243131",
    "inReplyTo": "codemodel",
    "type": "reply"
  }
}